importless/cli/__init__.py
importless/cli/main.py
importless/cli/commands/__init__.py
importless/cli/commands/clean.py
importless/cli/commands/export.py
importless/cli/commands/pyproject.py
importless/cli/commands/scan.py
importless/core/__init__.py
importless/core/analyzer.py
importless/core/dependency_graph.py
importless/core/exceptions.py
importless/core/requirements.py
importless/models/STDLIB.py
importless/models/__init__.py
importless/models/import_node.py
importless/utils/__init__.py
importless/utils/filewalker.py
importless/utils/formatter.py
importless-0.1.2.dist-info/licenses/LICENSE
importless-0.1.2.dist-info/METADATA
importless-0.1.2.dist-info/WHEEL
importless-0.1.2.dist-info/entry_points.txt
importless-0.1.2.dist-info/top_level.txt
importless-0.1.2.dist-info/RECORD
