Metadata-Version: 2.4
Name: importless
Version: 0.1.2
Summary: Deboalt your code by removing unused import statements
Author: Junaid Rahman
License: MIT
Project-URL: Homepage, https://github.com/Junaid433/importless
Project-URL: Repository, https://github.com/Junaid433/importless
Requires-Python: >=3.8
License-File: LICENSE
Requires-Dist: importless
Requires-Dist: rich>=14.0.0
Requires-Dist: toml>=0.10.2
Requires-Dist: typer>=0.16.0
Dynamic: license-file
